{
  "swagger": "2.0",
  "info": {
    "description": "A banking web app api for banka",
    "version": "1.0.0",
    "title": "Banka App"
  },
  "host": "bankaapp-api.herokuapp.com",
  "basePath": "/api",
  "schemes": [
    "https"
  ],
  "paths": {
    "v1/auth/signup": {
      "post": {
        "tags": [
          "Auth"
        ],
        "summary": "Users can signup",
        "description": "this endpoint uses get request to create users",
        "operationId": "signup",
        "consumes": [
          "application/x-www-form-urlencoded"
        ],
        "produces": [
          "application/json"
        ],
        "parameters": [
          {
            "name": "firstName",
            "in": "formData",
            "description": "users firstname",
            "required": true,
            "type": "string"
          },
          {
            "name": "lastName",
            "in": "formData",
            "description": "users lastname",
            "required": true,
            "type": "string"
          },
          {
            "name": "email",
            "in": "formData",
            "description": "users email address",
            "required": true,
            "type": "string"
          },
          {
            "name": "password",
            "in": "formData",
            "description": "password",
            "required": true,
            "type": "string"
          }
        ],
        "responses": {
          "405": {
            "description": "Invalid input"
          }
        }
      }
    },
    "v1/auth/signup/addstaff": {
      "post": {
        "tags": [
          "Auth"
        ],
        "summary": "Admin can signup staffs",
        "description": "this endpoint uses get request to create users",
        "operationId": "signupstaff",
        "consumes": [
          "application/x-www-form-urlencoded"
        ],
        "produces": [
          "application/json"
        ],
        "parameters": [
          {
            "name": "firstName",
            "in": "formData",
            "description": "users firstname",
            "required": true,
            "type": "string"
          },
          {
            "name": "lastName",
            "in": "formData",
            "description": "users lastname",
            "required": true,
            "type": "string"
          },
          {
            "name": "email",
            "in": "formData",
            "description": "users email address",
            "required": true,
            "type": "string"
          },
          {
            "name": "password",
            "in": "formData",
            "description": "password",
            "required": true,
            "type": "string"
          },
          {
            "name": "type",
            "in": "formData",
            "description": "staff",
            "required": true,
            "type": "string"
          },
          {
            "name": "isAdmin",
            "in": "formData",
            "description": "isAdmin",
            "required": true,
            "type": "boolean"
          }
        ],
        "responses": {
          "405": {
            "description": "Invalid input"
          }
        },
        "security": [
          {
            "JWT": []
          }
        ]
      }
    },
    "v1/auth/signin": {
      "post": {
        "tags": [
          "Auth"
        ],
        "summary": "Users can signup",
        "description": "this endpoint uses get request to create users",
        "operationId": "signin",
        "consumes": [
          "application/x-www-form-urlencoded"
        ],
        "produces": [
          "application/json"
        ],
        "parameters": [
          {
            "name": "email",
            "in": "formData",
            "description": "users email address",
            "required": true,
            "type": "string"
          },
          {
            "name": "password",
            "in": "formData",
            "description": "password",
            "required": true,
            "type": "string"
          }
        ],
        "responses": {
          "405": {
            "description": "Invalid input"
          }
        }
      }
    },
    "/v1/accounts": {
      "post": {
        "tags": [
          "Accounts"
        ],
        "summary": "Users can create a bank account",
        "description": "this endpoint allows users to create bank account",
        "operationId": "createaccount",
        "consumes": [
          "application/x-www-form-urlencoded"
        ],
        "produces": [
          "application/json"
        ],
        "parameters": [
          {
            "name": "type",
            "in": "formData",
            "description": "type of account (savings or current)",
            "required": true,
            "type": "string"
          }
        ],
        "responses": {
          "405": {
            "description": "Invalid input"
          }
        },
        "security": [
          {
            "JWT": []
          }
        ]
      },
      "get": {
        "tags": [
          "Accounts"
        ],
        "summary": "Returns all accounts",
        "description": "Staffs and admin can see all accounts",
        "operationId": "getaccounts",
        "produces": [
          "application/json"
        ],
        "parameters": [],
        "responses": {
          "200": {
            "description": "successful operation"
          }
        },
        "security": [
          {
            "JWT": []
          }
        ]
      }
    },
    "/v1/accounts/{accountNumber}": {
      "patch": {
        "tags": [
          "Accounts"
        ],
        "summary": "Staff can patch users bank account",
        "description": "this endpoint allows staff to patch users bank account",
        "operationId": "patchaccount",
        "consumes": [
          "application/x-www-form-urlencoded"
        ],
        "produces": [
          "application/json"
        ],
        "parameters": [
          {
            "name": "accountNumber",
            "in": "path",
            "description": "users account number",
            "required": true,
            "type": "integer"
          },
          {
            "name": "type",
            "in": "formData",
            "description": "type of account (savings or current)",
            "required": true,
            "type": "string"
          }
        ],
        "responses": {
          "405": {
            "description": "Invalid input"
          }
        },
        "security": [
          {
            "JWT": []
          }
        ]
      },
      "delete": {
        "tags": [
          "Accounts"
        ],
        "summary": "Staff and admin can delete account",
        "description": "this endpoint allows staff and admin to delete account",
        "operationId": "deleteaccount",
        "consumes": [
          "application/x-www-form-urlencoded"
        ],
        "produces": [
          "application/json"
        ],
        "parameters": [
          {
            "name": "accountNumber",
            "in": "path",
            "description": "users account number",
            "required": true,
            "type": "integer"
          }
        ],
        "responses": {
          "405": {
            "description": "Invalid input"
          }
        },
        "security": [
          {
            "JWT": []
          }
        ]
      }
    },
    "/v1/accounts/{accountNumber}/transactions": {
      "get": {
        "tags": [
          "Accounts"
        ],
        "summary": "User can view account transactions",
        "description": "this endpoint allows allows users to view account transactions",
        "operationId": "gettransactions",
        "consumes": [
          "application/x-www-form-urlencoded"
        ],
        "produces": [
          "application/json"
        ],
        "parameters": [
          {
            "name": "accountNumber",
            "in": "path",
            "description": "users account number",
            "required": true,
            "type": "integer"
          }
        ],
        "responses": {
          "405": {
            "description": "Invalid input"
          }
        },
        "security": [
          {
            "JWT": []
          }
        ]
      }
    },
    "/v1/transactions/{transactionid}": {
      "get": {
        "tags": [
          "Transactions"
        ],
        "summary": "User can view transactionid",
        "description": "this endpoint allows allows users transactionid",
        "operationId": "transactionid",
        "consumes": [
          "application/x-www-form-urlencoded"
        ],
        "produces": [
          "application/json"
        ],
        "parameters": [
          {
            "name": "transactionid",
            "in": "path",
            "description": "transaction id",
            "required": true,
            "type": "integer"
          }
        ],
        "responses": {
          "405": {
            "description": "Invalid input"
          }
        },
        "security": [
          {
            "JWT": []
          }
        ]
      }
    },
    "/v1/transactions/{accountNumber}/debit": {
      "post": {
        "tags": [
          "Transactions"
        ],
        "summary": "Staff and admin can debit users bank account",
        "description": "this endpoint allows staff and admin to debit users bank account",
        "operationId": "debitaccount",
        "consumes": [
          "application/x-www-form-urlencoded"
        ],
        "produces": [
          "application/json"
        ],
        "parameters": [
          {
            "name": "accountNumber",
            "in": "path",
            "description": "users account number",
            "required": true,
            "type": "integer"
          },
          {
            "name": "amount",
            "in": "formData",
            "description": "amount to debit user",
            "required": true,
            "type": "integer"
          }
        ],
        "responses": {
          "405": {
            "description": "Invalid input"
          }
        },
        "security": [
          {
            "JWT": []
          }
        ]
      }
    },
    "/v1/transactions/{accountNumber}/credit": {
      "post": {
        "tags": [
          "Transactions"
        ],
        "summary": "Staff and admin can credit users bank account",
        "description": "this endpoint allows staff and admin to credit users bank account",
        "operationId": "creditaccount",
        "consumes": [
          "application/x-www-form-urlencoded"
        ],
        "produces": [
          "application/json"
        ],
        "parameters": [
          {
            "name": "accountNumber",
            "in": "path",
            "description": "users account number",
            "required": true,
            "type": "integer"
          },
          {
            "name": "amount",
            "in": "formData",
            "description": "amount to credit user",
            "required": true,
            "type": "integer"
          }
        ],
        "responses": {
          "405": {
            "description": "Invalid input"
          }
        },
        "security": [
          {
            "JWT": []
          }
        ]
      }
    },
    "/v1/users": {
      "get": {
        "tags": [
          "Users"
        ],
        "summary": "Returns all users",
        "description": "Staffs and admin can see all users",
        "operationId": "getusers",
        "produces": [
          "application/json"
        ],
        "parameters": [],
        "responses": {
          "200": {
            "description": "successful operation"
          }
        },
        "security": [
          {
            "JWT": []
          }
        ]
      }
    },
    "/v1/users/{email}/accounts": {
      "get": {
        "tags": [
          "Users"
        ],
        "summary": "users to view all their accounts",
        "description": "this endpoint allows users to view all their account",
        "operationId": "getaccountsbyuser",
        "consumes": [
          "application/x-www-form-urlencoded"
        ],
        "produces": [
          "application/json"
        ],
        "parameters": [
          {
            "name": "email",
            "in": "path",
            "description": "email",
            "required": true,
            "type": "string"
          }
        ],
        "responses": {
          "405": {
            "description": "Invalid input"
          }
        },
        "security": [
          {
            "JWT": []
          }
        ]
      }
    },
    "/v1/users/{userId}": {
      "delete": {
        "tags": [
          "Users"
        ],
        "summary": "Staff can delete users",
        "description": "this endpoint allows staff and admin to delete users",
        "operationId": "deleteausers",
        "consumes": [
          "application/x-www-form-urlencoded"
        ],
        "produces": [
          "application/json"
        ],
        "parameters": [
          {
            "name": "userId",
            "in": "path",
            "description": "users account number",
            "required": true,
            "type": "integer"
          }
        ],
        "responses": {
          "405": {
            "description": "Invalid input"
          }
        },
        "security": [
          {
            "JWT": []
          }
        ]
      }
    }
  },
  "securityDefinitions": {
    "JWT": {
      "type": "apiKey",
      "name": "Authorization",
      "in": "header"
    }
  }
}
